{
  "11": "Agriculture, Forestry, Fishing and Hunting",
  "21": "Mining, Quarrying, and Oil and Gas Extraction",
  "22": "Utilities",
  "23": "Construction",
  "31": "Manufacturing",
  "32": "Manufacturing",
  "33": "Manufacturing",
  "42": "Wholesale Trade",
  "44": "Retail Trade",
  "45": "Retail Trade",
  "48": "Transportation and Warehousing",
  "49": "Transportation and Warehousing",
  "51": "Information",
  "52": "Finance and Insurance",
  "53": "Real Estate and Rental and Leasing",
  "54": "Professional, Scientific, and Technical Services",
  "55": "Management of Companies and Enterprises",
  "56": "Administrative and Support and Waste Management",
  "61": "Educational Services",
  "62": "Health Care and Social Assistance",
  "71": "Arts, Entertainment, and Recreation",
  "72": "Accommodation and Food Services",
  "81": "Other Services (except Public Administration)",
  "92": "Public Administration",
  "1133": "Agriculture, Forestry, Fishing and Hunting",
  "211": "Mining, Quarrying, and Oil and Gas Extraction",
  "212": "Mining, Quarrying, and Oil and Gas Extraction",
  "2121": "Mining, Quarrying, and Oil and Gas Extraction",
  "212114": "Mining, Quarrying, and Oil and Gas Extraction",
  "212115": "Mining, Quarrying, and Oil and Gas Extraction",
  "2122": "Mining, Quarrying, and Oil and Gas Extraction",
  "21222": "Mining, Quarrying, and Oil and Gas Extraction",
  "21221,3,9": "Mining, Quarrying, and Oil and Gas Extraction",
  "2123": "Mining, Quarrying, and Oil and Gas Extraction",
  "21231": "Mining, Quarrying, and Oil and Gas Extraction",
  "212312": "Mining, Quarrying, and Oil and Gas Extraction",
  "212311,3,9": "Mining, Quarrying, and Oil and Gas Extraction",
  "21232": "Mining, Quarrying, and Oil and Gas Extraction",
  "212321": "Mining, Quarrying, and Oil and Gas Extraction",
  "21239": "Mining, Quarrying, and Oil and Gas Extraction",
  "213": "Mining, Quarrying, and Oil and Gas Extraction",
  "213111": "Mining, Quarrying, and Oil and Gas Extraction",
  "213112": "Mining, Quarrying, and Oil and Gas Extraction",
  "213113,4,5": "Mining, Quarrying, and Oil and Gas Extraction",
  "236": "Construction",
  "2361": "Construction",
  "236115": "Construction",
  "236116": "Construction",
  "236117": "Construction",
  "236118": "Construction",
  "2362": "Construction",
  "23621": "Construction",
  "23622": "Construction",
  "237": "Construction",
  "2371": "Construction",
  "23711": "Construction",
  "23712": "Construction",
  "23713": "Construction",
  "2372": "Construction",
  "2373": "Construction",
  "2379": "Construction",
  "238": "Construction",
  "part 238": "Residential specialty trade contractors",
  "2381": "Construction",
  "23811": "Construction",
  "23812": "Construction",
  "23813": "Construction",
  "23814": "Construction",
  "23815": "Construction",
  "23816": "Construction",
  "23817": "Construction",
  "23819": "Construction",
  "2382": "Construction",
  "23821": "Construction",
  "23822": "Construction",
  "23829": "Construction",
  "2383": "Construction",
  "23831": "Construction",
  "23832": "Construction",
  "23833": "Construction",
  "23834": "Construction",
  "23835": "Construction",
  "23839": "Construction",
  "2389": "Construction",
  "23891": "Construction",
  "23899": "Construction",
  "321": "Manufacturing",
  "3211": "Manufacturing",
  "3212": "Manufacturing",
  "3219": "Manufacturing",
  "32191": "Manufacturing",
  "321911": "Manufacturing",
  "321912,8": "Manufacturing",
  "32192": "Manufacturing",
  "32199": "Manufacturing",
  "327": "Manufacturing",
  "3271": "Manufacturing",
  "3272": "Manufacturing",
  "3273": "Manufacturing",
  "32732": "Manufacturing",
  "32731,3,9": "Manufacturing",
  "3274,9": "Manufacturing",
  "331": "Manufacturing",
  "3311": "Manufacturing",
  "3312": "Manufacturing",
  "3313,4": "Manufacturing",
  "3315": "Manufacturing",
  "33151": "Manufacturing",
  "33152": "Manufacturing",
  "332": "Manufacturing",
  "3321": "Manufacturing",
  "3323": "Manufacturing",
  "33231": "Manufacturing",
  "332312": "Manufacturing",
  "332311,3": "Manufacturing",
  "33232": "Manufacturing",
  "332321": "Manufacturing",
  "332322": "Manufacturing",
  "332323": "Manufacturing",
  "3324": "Manufacturing",
  "3325,6": "Manufacturing",
  "3327": "Manufacturing",
  "33271": "Manufacturing",
  "33272": "Manufacturing",
  "3328": "Manufacturing",
  "332811,2": "Manufacturing",
  "332813": "Manufacturing",
  "3329": "Manufacturing",
  "33291": "Manufacturing",
  "33299": "Manufacturing",
  "332992,3,4": "Manufacturing",
  "332200;991,9": "Manufacturing",
  "333": "Manufacturing",
  "3331": "Manufacturing",
  "33311": "Manufacturing",
  "33312": "Manufacturing",
  "33313": "Manufacturing",
  "3332": "Manufacturing",
  "333248": "Manufacturing",
  "3333": "Manufacturing",
  "3334": "Manufacturing",
  "333415": "Manufacturing",
  "3335": "Manufacturing",
  "333514": "Manufacturing",
  "333517": "Manufacturing",
  "333511,5,9": "Manufacturing",
  "3336": "Manufacturing",
  "3339": "Manufacturing",
  "33391": "Manufacturing",
  "33392": "Manufacturing",
  "33399": "Manufacturing",
  "334": "Manufacturing",
  "3341": "Manufacturing",
  "334111": "Manufacturing",
  "334112,8": "Manufacturing",
  "3342": "Manufacturing",
  "33422": "Manufacturing",
  "3344": "Manufacturing",
  "334413": "Manufacturing",
  "334412,8": "Manufacturing",
  "334416,7,9": "Manufacturing",
  "3345": "Manufacturing",
  "334510": "Manufacturing",
  "334511": "Manufacturing",
  "334513": "Manufacturing",
  "334515": "Manufacturing",
  "334512,4,6-9": "Manufacturing",
  "3343,6": "Manufacturing",
  "335": "Manufacturing",
  "3351": "Manufacturing",
  "3352": "Manufacturing",
  "3353": "Manufacturing",
  "335311": "Manufacturing",
  "335312,3,4": "Manufacturing",
  "3359": "Manufacturing",
  "33591": "Manufacturing",
  "33592,3,9": "Manufacturing",
  "336": "Manufacturing",
  "3361,2,3": "Manufacturing",
  "3361": "Manufacturing",
  "3362": "Manufacturing",
  "3363": "Manufacturing",
  "33631": "Manufacturing",
  "33632": "Manufacturing",
  "33635": "Manufacturing",
  "33637": "Manufacturing",
  "33633,4,6,9": "Manufacturing",
  "3364": "Manufacturing",
  "336411": "Manufacturing",
  "336412": "Manufacturing",
  "336413": "Manufacturing",
  "336414,5,9": "Manufacturing",
  "3366": "Manufacturing",
  "336611": "Manufacturing",
  "336612": "Manufacturing",
  "3365,9": "Manufacturing",
  "337": "Manufacturing",
  "3371": "Manufacturing",
  "33711": "Manufacturing",
  "33712": "Manufacturing",
  "337121": "Manufacturing",
  "337122,6,7": "Manufacturing",
  "3372": "Manufacturing",
  "337211,2,4": "Manufacturing",
  "337215": "Manufacturing",
  "339": "Manufacturing",
  "3391": "Manufacturing",
  "339112": "Manufacturing",
  "339113": "Manufacturing",
  "339116": "Manufacturing",
  "3399": "Manufacturing",
  "33991,2": "Manufacturing",
  "33995": "Manufacturing",
  "33993,4,9": "Manufacturing",
  "311": "Manufacturing",
  "3111": "Manufacturing",
  "3112": "Manufacturing",
  "3113": "Manufacturing",
  "31135": "Manufacturing",
  "3114": "Manufacturing",
  "31141": "Manufacturing",
  "311411": "Manufacturing",
  "311412": "Manufacturing",
  "31142": "Manufacturing",
  "3115": "Manufacturing",
  "311511": "Manufacturing",
  "3116": "Manufacturing",
  "311611": "Manufacturing",
  "311612,3": "Manufacturing",
  "311615": "Manufacturing",
  "3117": "Manufacturing",
  "3118": "Manufacturing",
  "31181": "Manufacturing",
  "311811": "Manufacturing",
  "311812,3": "Manufacturing",
  "31182,3": "Manufacturing",
  "3119": "Manufacturing",
  "31191": "Manufacturing",
  "31192,3,4,9": "Manufacturing",
  "313": "Manufacturing",
  "3132": "Manufacturing",
  "314": "Manufacturing",
  "3141": "Manufacturing",
  "3149": "Manufacturing",
  "315": "Manufacturing",
  "31525": "Manufacturing",
  "322": "Manufacturing",
  "3221": "Manufacturing",
  "3222": "Manufacturing",
  "32221": "Manufacturing",
  "32222": "Manufacturing",
  "32223,9": "Manufacturing",
  "323": "Manufacturing",
  "323113": "Manufacturing",
  "323111,17,20": "Manufacturing",
  "324": "Manufacturing",
  "32411": "Manufacturing",
  "32412,9": "Manufacturing",
  "325": "Manufacturing",
  "3251": "Manufacturing",
  "32511,2,3,8": "Manufacturing",
  "32519": "Manufacturing",
  "3252": "Manufacturing",
  "325211": "Manufacturing",
  "3253": "Manufacturing",
  "3254": "Manufacturing",
  "325412": "Manufacturing",
  "325411,3,4": "Manufacturing",
  "3255": "Manufacturing",
  "3256": "Manufacturing",
  "32561": "Manufacturing",
  "32562": "Manufacturing",
  "3259": "Manufacturing",
  "326": "Manufacturing",
  "3261": "Manufacturing",
  "32611": "Manufacturing",
  "32612": "Manufacturing",
  "32614,5": "Manufacturing",
  "32613,6": "Manufacturing",
  "32619": "Manufacturing",
  "3262": "Manufacturing",
  "32621": "Manufacturing",
  "32622,9": "Manufacturing",
  "312,6": "Manufacturing",
  "3121": "Manufacturing",
  "31211": "Manufacturing",
  "312111": "Manufacturing",
  "31212,3,4": "Manufacturing",
  "3122,60": "Manufacturing",
  "423": "Wholesale Trade",
  "4231": "Wholesale Trade",
  "42311": "Wholesale Trade",
  "42312": "Wholesale Trade",
  "4232": "Wholesale Trade",
  "42321": "Wholesale Trade",
  "42322": "Wholesale Trade",
  "4233": "Wholesale Trade",
  "42331": "Wholesale Trade",
  "42332": "Wholesale Trade",
  "42333,9": "Wholesale Trade",
  "4234": "Wholesale Trade",
  "42342": "Wholesale Trade",
  "42343": "Wholesale Trade",
  "42345": "Wholesale Trade",
  "42341,4,6,9": "Wholesale Trade",
  "4235": "Wholesale Trade",
  "4236": "Wholesale Trade",
  "42361": "Wholesale Trade",
  "42362,9": "Wholesale Trade",
  "4237": "Wholesale Trade",
  "42371": "Wholesale Trade",
  "42372": "Wholesale Trade",
  "42373,4": "Wholesale Trade",
  "4238": "Wholesale Trade",
  "42381": "Wholesale Trade",
  "42382": "Wholesale Trade",
  "42383": "Wholesale Trade",
  "42384": "Wholesale Trade",
  "42385": "Wholesale Trade",
  "42386": "Wholesale Trade",
  "4239": "Wholesale Trade",
  "42391": "Wholesale Trade",
  "42393": "Wholesale Trade",
  "42394": "Wholesale Trade",
  "42392,9": "Wholesale Trade",
  "424": "Wholesale Trade",
  "4241": "Wholesale Trade",
  "42411,2": "Wholesale Trade",
  "42413": "Wholesale Trade",
  "4242": "Wholesale Trade",
  "4243": "Wholesale Trade",
  "42431,4": "Wholesale Trade",
  "42435": "Wholesale Trade",
  "4244": "Wholesale Trade",
  "42441": "Wholesale Trade",
  "42442": "Wholesale Trade",
  "42445": "Wholesale Trade",
  "42443,4,6,7": "Wholesale Trade",
  "42448": "Wholesale Trade",
  "42449": "Wholesale Trade",
  "4245": "Wholesale Trade",
  "42451": "Wholesale Trade",
  "4246": "Wholesale Trade",
  "4247": "Wholesale Trade",
  "4248": "Wholesale Trade",
  "42481": "Wholesale Trade",
  "42482": "Wholesale Trade",
  "4249": "Wholesale Trade",
  "42491": "Wholesale Trade",
  "42493": "Wholesale Trade",
  "42492,4,5,9": "Wholesale Trade",
  "425": "Wholesale Trade",
  "441": "Retail Trade",
  "4411": "Retail Trade",
  "44111": "Retail Trade",
  "44112": "Retail Trade",
  "4412": "Retail Trade",
  "44121": "Retail Trade",
  "44122": "Retail Trade",
  "4413": "Retail Trade",
  "44133": "Retail Trade",
  "44134": "Retail Trade",
  "444": "Retail Trade",
  "4441": "Retail Trade",
  "44414": "Retail Trade",
  "44411,2,8": "Retail Trade",
  "4442": "Retail Trade",
  "44423": "Retail Trade",
  "44424": "Retail Trade",
  "445": "Retail Trade",
  "4451": "Retail Trade",
  "44511": "Retail Trade",
  "44513": "Retail Trade",
  "445131": "Retail Trade",
  "445132": "Retail Trade",
  "4452": "Retail Trade",
  "44523": "Retail Trade",
  "44524,5": "Retail Trade",
  "44529": "Retail Trade",
  "445291,2": "Retail Trade",
  "445298": "Retail Trade",
  "4453": "Retail Trade",
  "449": "Retail Trade",
  "4491": "Retail Trade",
  "44911": "Retail Trade",
  "44912": "Retail Trade",
  "449121": "Retail Trade",
  "449122,9": "Retail Trade",
  "4492": "Retail Trade",
  "455": "Retail Trade",
  "4551": "Retail Trade",
  "4552": "Retail Trade",
  "456": "Retail Trade",
  "45611": "Retail Trade",
  "45612": "Retail Trade",
  "45613": "Retail Trade",
  "45619": "Retail Trade",
  "456191": "Retail Trade",
  "456199": "Retail Trade",
  "457": "Retail Trade",
  "4571": "Retail Trade",
  "45711": "Retail Trade",
  "45712": "Retail Trade",
  "4572": "Retail Trade",
  "458": "Retail Trade",
  "4581": "Retail Trade",
  "4582": "Retail Trade",
  "4583": "Retail Trade",
  "459": "Retail Trade",
  "4591": "Retail Trade",
  "45911": "Retail Trade",
  "45912": "Retail Trade",
  "45913": "Retail Trade",
  "45914": "Retail Trade",
  "4592": "Retail Trade",
  "4593": "Retail Trade",
  "4594": "Retail Trade",
  "45941": "Retail Trade",
  "45942": "Retail Trade",
  "4595": "Retail Trade",
  "4599": "Retail Trade",
  "45991": "Retail Trade",
  "45992": "Retail Trade",
  "45993,9": "Retail Trade",
  "459991": "Retail Trade",
  "481": "Transportation and Warehousing",
  "4811": "Transportation and Warehousing",
  "4812": "Transportation and Warehousing",
  "482": "Transportation and Warehousing",
  "483": "Transportation and Warehousing",
  "484": "Transportation and Warehousing",
  "4841": "Transportation and Warehousing",
  "48411": "Transportation and Warehousing",
  "48412": "Transportation and Warehousing",
  "484121": "Transportation and Warehousing",
  "484122": "Transportation and Warehousing",
  "4842": "Transportation and Warehousing",
  "48421": "Transportation and Warehousing",
  "48422": "Transportation and Warehousing",
  "48423": "Transportation and Warehousing",
  "485": "Transportation and Warehousing",
  "4853": "Transportation and Warehousing",
  "4854": "Transportation and Warehousing",
  "4851,2,5": "Transportation and Warehousing",
  "4859": "Transportation and Warehousing",
  "486": "Transportation and Warehousing",
  "487": "Transportation and Warehousing",
  "488": "Transportation and Warehousing",
  "4881": "Transportation and Warehousing",
  "4883": "Transportation and Warehousing",
  "48832": "Transportation and Warehousing",
  "4884": "Transportation and Warehousing",
  "4885": "Transportation and Warehousing",
  "4882,9": "Transportation and Warehousing",
  "492": "Transportation and Warehousing",
  "4921": "Transportation and Warehousing",
  "49111,221": "Transportation and Warehousing",
  "493": "Transportation and Warehousing",
  "49311": "Transportation and Warehousing",
  "49312": "Transportation and Warehousing",
  "49313,9": "Transportation and Warehousing",
  "2211": "Utilities",
  "22111": "Utilities",
  "221112": "Utilities",
  "221111,3-8": "Utilities",
  "22112": "Utilities",
  "221121": "Utilities",
  "221122": "Utilities",
  "2212": "Utilities",
  "2213": "Utilities",
  "512": "Information",
  "51211": "Information",
  "51213": "Information",
  "513": "Information",
  "5131": "Information",
  "51311": "Information",
  "51312": "Information",
  "51313": "Information",
  "51314,9": "Information",
  "5132": "Information",
  "516": "Information",
  "5161": "Information",
  "51611": "Information",
  "51612": "Information",
  "5162": "Information",
  "517": "Information",
  "5171": "Information",
  "51711": "Information",
  "517111": "Information",
  "517112": "Information",
  "51712": "Information",
  "5174,8": "Information",
  "518": "Information",
  "519": "Information",
  "51921": "Information",
  "51929": "Information",
  "521": "Finance and Insurance",
  "522": "Finance and Insurance",
  "5221": "Finance and Insurance",
  "52211": "Finance and Insurance",
  "52213": "Finance and Insurance",
  "52218": "Finance and Insurance",
  "5222": "Finance and Insurance",
  "52221": "Finance and Insurance",
  "52222": "Finance and Insurance",
  "52229": "Finance and Insurance",
  "522291": "Finance and Insurance",
  "522292": "Finance and Insurance",
  "522299": "Finance and Insurance",
  "5223": "Finance and Insurance",
  "52231": "Finance and Insurance",
  "52232": "Finance and Insurance",
  "52239": "Finance and Insurance",
  "523,5": "Finance and Insurance",
  "52315": "Finance and Insurance",
  "5231,2": "Finance and Insurance",
  "5239,50": "Finance and Insurance",
  "52391": "Finance and Insurance",
  "52394": "Finance and Insurance",
  "52399,500": "Finance and Insurance",
  "524": "Finance and Insurance",
  "5241": "Finance and Insurance",
  "52411": "Finance and Insurance",
  "52412": "Finance and Insurance",
  "524126": "Finance and Insurance",
  "524127,8": "Finance and Insurance",
  "52413": "Finance and Insurance",
  "5242": "Finance and Insurance",
  "52421": "Finance and Insurance",
  "52429": "Finance and Insurance",
  "524291": "Finance and Insurance",
  "524292": "Finance and Insurance",
  "524298": "Finance and Insurance",
  "531": "Real Estate and Rental and Leasing",
  "5311": "Real Estate and Rental and Leasing",
  "53111": "Real Estate and Rental and Leasing",
  "53112": "Real Estate and Rental and Leasing",
  "53113": "Real Estate and Rental and Leasing",
  "53119": "Real Estate and Rental and Leasing",
  "5312": "Real Estate and Rental and Leasing",
  "5313": "Real Estate and Rental and Leasing",
  "53131": "Real Estate and Rental and Leasing",
  "531311": "Real Estate and Rental and Leasing",
  "531312": "Real Estate and Rental and Leasing",
  "53132": "Real Estate and Rental and Leasing",
  "53139": "Real Estate and Rental and Leasing",
  "532": "Real Estate and Rental and Leasing",
  "5321": "Real Estate and Rental and Leasing",
  "53211": "Real Estate and Rental and Leasing",
  "53212": "Real Estate and Rental and Leasing",
  "5322": "Real Estate and Rental and Leasing",
  "532283": "Real Estate and Rental and Leasing",
  "5323": "Real Estate and Rental and Leasing",
  "5324": "Real Estate and Rental and Leasing",
  "53241": "Real Estate and Rental and Leasing",
  "53242,9": "Real Estate and Rental and Leasing",
  "533": "Real Estate and Rental and Leasing",
  "5411": "Professional, Scientific, and Technical Services",
  "54111": "Professional, Scientific, and Technical Services",
  "54119": "Professional, Scientific, and Technical Services",
  "5412": "Professional, Scientific, and Technical Services",
  "541211": "Professional, Scientific, and Technical Services",
  "541213": "Professional, Scientific, and Technical Services",
  "541214": "Professional, Scientific, and Technical Services",
  "541219": "Professional, Scientific, and Technical Services",
  "5413": "Professional, Scientific, and Technical Services",
  "54131": "Professional, Scientific, and Technical Services",
  "54132": "Professional, Scientific, and Technical Services",
  "54133,4": "Professional, Scientific, and Technical Services",
  "54135,6,7": "Professional, Scientific, and Technical Services",
  "54138": "Professional, Scientific, and Technical Services",
  "5414": "Professional, Scientific, and Technical Services",
  "54141": "Professional, Scientific, and Technical Services",
  "54143": "Professional, Scientific, and Technical Services",
  "5415": "Professional, Scientific, and Technical Services",
  "541511": "Professional, Scientific, and Technical Services",
  "541512": "Professional, Scientific, and Technical Services",
  "541513": "Professional, Scientific, and Technical Services",
  "541519": "Professional, Scientific, and Technical Services",
  "5416": "Professional, Scientific, and Technical Services",
  "54161": "Professional, Scientific, and Technical Services",
  "541611": "Professional, Scientific, and Technical Services",
  "541612": "Professional, Scientific, and Technical Services",
  "541613": "Professional, Scientific, and Technical Services",
  "541614": "Professional, Scientific, and Technical Services",
  "541618": "Professional, Scientific, and Technical Services",
  "54162": "Professional, Scientific, and Technical Services",
  "54169": "Professional, Scientific, and Technical Services",
  "5417": "Professional, Scientific, and Technical Services",
  "54171": "Professional, Scientific, and Technical Services",
  "541713": "Professional, Scientific, and Technical Services",
  "541714": "Professional, Scientific, and Technical Services",
  "541715": "Professional, Scientific, and Technical Services",
  "54172": "Professional, Scientific, and Technical Services",
  "5418": "Professional, Scientific, and Technical Services",
  "54181": "Professional, Scientific, and Technical Services",
  "54182": "Professional, Scientific, and Technical Services",
  "54183,4": "Professional, Scientific, and Technical Services",
  "54185": "Professional, Scientific, and Technical Services",
  "54186": "Professional, Scientific, and Technical Services",
  "54187,9": "Professional, Scientific, and Technical Services",
  "5419": "Professional, Scientific, and Technical Services",
  "54191": "Professional, Scientific, and Technical Services",
  "54192": "Professional, Scientific, and Technical Services",
  "54194": "Professional, Scientific, and Technical Services",
  "54193,9": "Professional, Scientific, and Technical Services",
  "551111,2": "Management of Companies and Enterprises",
  "551114": "Management of Companies and Enterprises",
  "561": "Administrative and Support and Waste Management",
  "5611": "Administrative and Support and Waste Management",
  "5612": "Administrative and Support and Waste Management",
  "5613": "Administrative and Support and Waste Management",
  "56131": "Administrative and Support and Waste Management",
  "561311": "Administrative and Support and Waste Management",
  "561312": "Administrative and Support and Waste Management",
  "56132": "Administrative and Support and Waste Management",
  "56133": "Administrative and Support and Waste Management",
  "5614": "Administrative and Support and Waste Management",
  "56141": "Administrative and Support and Waste Management",
  "56142": "Administrative and Support and Waste Management",
  "561421": "Administrative and Support and Waste Management",
  "561422": "Administrative and Support and Waste Management",
  "56143": "Administrative and Support and Waste Management",
  "56144": "Administrative and Support and Waste Management",
  "56145,9": "Administrative and Support and Waste Management",
  "561499": "Administrative and Support and Waste Management",
  "5615": "Administrative and Support and Waste Management",
  "56151": "Administrative and Support and Waste Management",
  "56152": "Administrative and Support and Waste Management",
  "56159": "Administrative and Support and Waste Management",
  "5616": "Administrative and Support and Waste Management",
  "56161": "Administrative and Support and Waste Management",
  "561611": "Administrative and Support and Waste Management",
  "561612,3": "Administrative and Support and Waste Management",
  "56162": "Administrative and Support and Waste Management",
  "5617": "Administrative and Support and Waste Management",
  "56171": "Administrative and Support and Waste Management",
  "56172": "Administrative and Support and Waste Management",
  "56173": "Administrative and Support and Waste Management",
  "56174": "Administrative and Support and Waste Management",
  "56179": "Administrative and Support and Waste Management",
  "5619": "Administrative and Support and Waste Management",
  "56191": "Administrative and Support and Waste Management",
  "56192": "Administrative and Support and Waste Management",
  "56199": "Administrative and Support and Waste Management",
  "562": "Administrative and Support and Waste Management",
  "5621": "Administrative and Support and Waste Management",
  "562111": "Administrative and Support and Waste Management",
  "562112,9": "Administrative and Support and Waste Management",
  "5622": "Administrative and Support and Waste Management",
  "562211": "Administrative and Support and Waste Management",
  "562212,3,9": "Administrative and Support and Waste Management",
  "5629": "Administrative and Support and Waste Management",
  "56291": "Administrative and Support and Waste Management",
  "56292,9": "Administrative and Support and Waste Management",
  "6111": "Educational Services",
  "6112,3": "Educational Services",
  "6114": "Educational Services",
  "61141,2": "Educational Services",
  "61143": "Educational Services",
  "6115": "Educational Services",
  "611512": "Educational Services",
  "611511,3": "Educational Services",
  "611519": "Educational Services",
  "6116": "Educational Services",
  "61161": "Educational Services",
  "61162": "Educational Services",
  "61163,9": "Educational Services",
  "611691": "Educational Services",
  "611699": "Educational Services",
  "6117": "Educational Services",
  "621,2,3": "Health Care and Social Assistance",
  "621": "Health Care and Social Assistance",
  "6211": "Health Care and Social Assistance",
  "621111": "Health Care and Social Assistance",
  "621112": "Health Care and Social Assistance",
  "6212": "Health Care and Social Assistance",
  "6213": "Health Care and Social Assistance",
  "62131": "Health Care and Social Assistance",
  "62132": "Health Care and Social Assistance",
  "62133": "Health Care and Social Assistance",
  "62134": "Health Care and Social Assistance",
  "62139": "Health Care and Social Assistance",
  "621391": "Health Care and Social Assistance",
  "621399": "Health Care and Social Assistance",
  "6214": "Health Care and Social Assistance",
  "62142": "Health Care and Social Assistance",
  "62141,9": "Health Care and Social Assistance",
  "621491": "Health Care and Social Assistance",
  "621492": "Health Care and Social Assistance",
  "621493": "Health Care and Social Assistance",
  "621410,98": "Health Care and Social Assistance",
  "6215": "Health Care and Social Assistance",
  "621511": "Health Care and Social Assistance",
  "621512": "Health Care and Social Assistance",
  "6216": "Health Care and Social Assistance",
  "6219": "Health Care and Social Assistance",
  "62191": "Health Care and Social Assistance",
  "62199": "Health Care and Social Assistance",
  "621991": "Health Care and Social Assistance",
  "621999": "Health Care and Social Assistance",
  "622": "Health Care and Social Assistance",
  "6221": "Health Care and Social Assistance",
  "6222": "Health Care and Social Assistance",
  "6223": "Health Care and Social Assistance",
  "623": "Health Care and Social Assistance",
  "6231": "Health Care and Social Assistance",
  "6232": "Health Care and Social Assistance",
  "62321": "Health Care and Social Assistance",
  "62322": "Health Care and Social Assistance",
  "6233": "Health Care and Social Assistance",
  "623311": "Health Care and Social Assistance",
  "623312": "Health Care and Social Assistance",
  "6239": "Health Care and Social Assistance",
  "624": "Health Care and Social Assistance",
  "6241": "Health Care and Social Assistance",
  "62411": "Health Care and Social Assistance",
  "62412": "Health Care and Social Assistance",
  "62419": "Health Care and Social Assistance",
  "6242": "Health Care and Social Assistance",
  "62421": "Health Care and Social Assistance",
  "62422,3": "Health Care and Social Assistance",
  "6243": "Health Care and Social Assistance",
  "6244": "Health Care and Social Assistance",
  "711": "Arts, Entertainment, and Recreation",
  "7111": "Arts, Entertainment, and Recreation",
  "71113": "Arts, Entertainment, and Recreation",
  "71111,2,9": "Arts, Entertainment, and Recreation",
  "7112": "Arts, Entertainment, and Recreation",
  "711211": "Arts, Entertainment, and Recreation",
  "711212,9": "Arts, Entertainment, and Recreation",
  "7113,4": "Arts, Entertainment, and Recreation",
  "7115": "Arts, Entertainment, and Recreation",
  "712": "Arts, Entertainment, and Recreation",
  "71211": "Arts, Entertainment, and Recreation",
  "71212,3,9": "Arts, Entertainment, and Recreation",
  "713": "Arts, Entertainment, and Recreation",
  "7131": "Arts, Entertainment, and Recreation",
  "7132": "Arts, Entertainment, and Recreation",
  "71321": "Arts, Entertainment, and Recreation",
  "71329": "Arts, Entertainment, and Recreation",
  "7139": "Arts, Entertainment, and Recreation",
  "71391": "Arts, Entertainment, and Recreation",
  "71392": "Arts, Entertainment, and Recreation",
  "71393": "Arts, Entertainment, and Recreation",
  "71394": "Arts, Entertainment, and Recreation",
  "71395": "Arts, Entertainment, and Recreation",
  "71399": "Arts, Entertainment, and Recreation",
  "721": "Accommodation and Food Services",
  "7211": "Accommodation and Food Services",
  "72111": "Accommodation and Food Services",
  "72112": "Accommodation and Food Services",
  "72119": "Accommodation and Food Services",
  "721191": "Accommodation and Food Services",
  "721310,199": "Accommodation and Food Services",
  "7212": "Accommodation and Food Services",
  "722": "Accommodation and Food Services",
  "7223": "Accommodation and Food Services",
  "72231": "Accommodation and Food Services",
  "72232,3": "Accommodation and Food Services",
  "7224": "Accommodation and Food Services",
  "7225": "Accommodation and Food Services",
  "722511": "Accommodation and Food Services",
  "722513": "Accommodation and Food Services",
  "722514": "Accommodation and Food Services",
  "722515": "Accommodation and Food Services",
  "811": "Other Services (except Public Administration)",
  "8111": "Other Services (except Public Administration)",
  "81111": "Other Services (except Public Administration)",
  "811111": "Other Services (except Public Administration)",
  "811114": "Other Services (except Public Administration)",
  "81112": "Other Services (except Public Administration)",
  "811121": "Other Services (except Public Administration)",
  "811122": "Other Services (except Public Administration)",
  "81119": "Other Services (except Public Administration)",
  "811192": "Other Services (except Public Administration)",
  "811191,8": "Other Services (except Public Administration)",
  "8112": "Other Services (except Public Administration)",
  "8113": "Other Services (except Public Administration)",
  "8114": "Other Services (except Public Administration)",
  "812": "Other Services (except Public Administration)",
  "8121": "Other Services (except Public Administration)",
  "81211": "Other Services (except Public Administration)",
  "812111,2": "Other Services (except Public Administration)",
  "812113": "Other Services (except Public Administration)",
  "81219": "Other Services (except Public Administration)",
  "8122": "Other Services (except Public Administration)",
  "81221": "Other Services (except Public Administration)",
  "81222": "Other Services (except Public Administration)",
  "8123": "Other Services (except Public Administration)",
  "81231": "Other Services (except Public Administration)",
  "81232": "Other Services (except Public Administration)",
  "81233": "Other Services (except Public Administration)",
  "812331": "Other Services (except Public Administration)",
  "812332": "Other Services (except Public Administration)",
  "8129": "Other Services (except Public Administration)",
  "81291": "Other Services (except Public Administration)",
  "81293": "Other Services (except Public Administration)",
  "81292,9": "Other Services (except Public Administration)",
  "813": "Other Services (except Public Administration)",
  "8132": "Other Services (except Public Administration)",
  "813211": "Other Services (except Public Administration)",
  "813212": "Other Services (except Public Administration)",
  "813219": "Other Services (except Public Administration)",
  "8133": "Other Services (except Public Administration)",
  "813311": "Other Services (except Public Administration)",
  "813312,9": "Other Services (except Public Administration)",
  "8134": "Other Services (except Public Administration)",
  "8139": "Other Services (except Public Administration)",
  "81391": "Other Services (except Public Administration)",
  "81392": "Other Services (except Public Administration)",
  "81393": "Other Services (except Public Administration)",
  "81394,9": "Other Services (except Public Administration)",
  "3122": "Tobacco Manufacturing",
  "312": "Beverage and Tobacco Products",
  "316": "Leather and Allied Products",
  "324110": "Petroleum Refineries",
  "333111": "Farm Machinery and Equipment",
  "333120": "Construction Machinery",
  "33324": "Industrial Machinery",
  "333314": "Photographic Equipment",
  "33341": "HVAC and Commercial Refrigeration Equipment",
  "33351": "Metalworking Machinery",
  "334112": "Computer Storage Device Mfg",
  "334118": "Other Computer Peripheral Equipment",
  "33421": "Communications Equipment, Nondefense",
  "334310": "Audio and Video Equipment",
  "336111": "Automobile Manufacturing",
  "336112": "Light Truck and Utility Vehicle Mfg",
  "336120": "Heavy Duty Truck Manufacturing",
  "33621": "Motor Vehicle Bodies, Parts, and Trailers",
  "3313": "Aluminum and Nonferrous Metal Products",
  "33411": "Computers and Related Products",
  "durable ex defense": "Durable Goods excl. Defense",
  "durable ex 336": "Durable Goods excl. Transportation",
  "33361": "Turbines/Generators/Power Transmission",
  "22121": "Utilities",
  "4831": "Transportation and Warehousing",
  "4849": "Transportation and Warehousing",
  "51111": "Information",
  "51112": "Information",
  "5111": "Information",
  "5112": "Information",
  "511": "Information",
  "5151": "Information",
  "5152": "Information",
  "515": "Information",
  "517311": "Information",
  "517312": "Information",
  "54133": "Professional, Scientific, and Technical Services",
  "61171": "Educational Services",
  "7113": "Arts, Entertainment, and Recreation",
  "71141": "Arts, Entertainment, and Recreation",
  "71151": "Arts, Entertainment, and Recreation",
  "7213": "Accommodation and Food Services"
}